pylizlib/__init__.py
pylizlib/project.py
pylizlib/core/__init__.py
pylizlib/core/cli.py
pylizlib/core/cli2.py
pylizlib/core/app/__init__.py
pylizlib/core/app/configini.py
pylizlib/core/app/pylizapp.py
pylizlib/core/app/pylizini.py
pylizlib/core/app/pytoml.py
pylizlib/core/data/__init__.py
pylizlib/core/data/gen.py
pylizlib/core/data/json.py
pylizlib/core/data/regex.py
pylizlib/core/data/unit.py
pylizlib/core/data/utils.py
pylizlib/core/domain/__init__.py
pylizlib/core/domain/cli.py
pylizlib/core/domain/operation.py
pylizlib/core/domain/os.py
pylizlib/core/handler/__init__.py
pylizlib/core/handler/progress.py
pylizlib/core/log/__init__.py
pylizlib/core/log/loggiz.py
pylizlib/core/log/pylizLogger.py
pylizlib/core/network/__init__.py
pylizlib/core/network/req.py
pylizlib/core/network/ssl.py
pylizlib/core/os/__init__.py
pylizlib/core/os/file.py
pylizlib/core/os/path.py
pylizlib/core/os/snap.py
pylizlib/core/os/ui.py
pylizlib/core/os/utils.py
pylizlib/core/temp/__init__.py
pylizlib/core/temp/pyliz_actions.py
pylizlib/core/temp/pylizscript.py
pylizlib/eaglecool/__init__.py
pylizlib/eaglecool/reader.py
pylizlib/eaglecool/model/__init__.py
pylizlib/eaglecool/model/metadata.py
pylizlib/media/__init__.py
pylizlib/media/lizmedia.py
pylizlib/media/compute/__init__.py
pylizlib/media/compute/frameselector.py
pylizlib/media/domain/__init__.py
pylizlib/media/domain/ai.py
pylizlib/media/domain/audio.py
pylizlib/media/domain/video.py
pylizlib/media/util/__init__.py
pylizlib/media/util/image.py
pylizlib/media/util/video.py
pylizlib/qt/__init__.py
pylizlib/qt/cli.py
pylizlib/qt/scripts.py
pylizlib/qt/debug/__init__.py
pylizlib/qt/debug/operation.py
pylizlib/qt/domain/__init__.py
pylizlib/qt/domain/config.py
pylizlib/qt/domain/menuActionTool.py
pylizlib/qt/domain/preference.py
pylizlib/qt/domain/resource.py
pylizlib/qt/domain/theme.py
pylizlib/qt/domain/view.py
pylizlib/qt/handler/__init__.py
pylizlib/qt/handler/config.py
pylizlib/qt/handler/menuAction.py
pylizlib-0.3.71.dist-info/licenses/LICENSE
pylizlib-0.3.71.dist-info/METADATA
pylizlib-0.3.71.dist-info/WHEEL
pylizlib-0.3.71.dist-info/entry_points.txt
pylizlib-0.3.71.dist-info/top_level.txt
pylizlib-0.3.71.dist-info/RECORD
