Metadata-Version: 2.4
Name: pylizlib
Version: 0.3.71
Summary: Add your description here
Author-email: Gabliz <gabliz.dev@gmail.com>
Requires-Python: >=3.12
License-File: LICENSE
Requires-Dist: pillow>=12.0.0
Requires-Dist: psutil>=7.1.0
Requires-Dist: python-dotenv>=1.1.0
Requires-Dist: pywin32>=1.0; sys_platform == "win32"
Requires-Dist: requests>=2.32.3
Requires-Dist: rich>=14.0.0
Requires-Dist: ruff>=0.14.0
Requires-Dist: sd-parsers>=0.6
Requires-Dist: typer>=0.15.2
Provides-Extra: qt
Requires-Dist: pyside6>=6.9.2; extra == "qt"
Provides-Extra: media
Requires-Dist: ffmpeg-python>=0.2.0; extra == "media"
Requires-Dist: numpy>=2.3.3; extra == "media"
Requires-Dist: opencv-python>=4.11.0.86; extra == "media"
Requires-Dist: pillow>=11.3.0; extra == "media"
Requires-Dist: pydantic>=2.11.9; extra == "media"
Requires-Dist: sd-parsers>=0.6; extra == "media"
Provides-Extra: qtfw
Requires-Dist: pyside6>=6.9.2; extra == "qtfw"
Requires-Dist: PySide6-Fluent-Widgets[full]>=1.9.1; extra == "qtfw"
Provides-Extra: eaglecool
Requires-Dist: pydantic>=2.11.9; extra == "eaglecool"
Dynamic: license-file
